rtl/defines.vh
// ============================================================
// File        : defines.vh
// Project     : Out-of-Order Issue Queue - Tesla AI Hardware Portfolio
// Author      : Mayank
// Description : Global parameters, opcode encodings, and state constants.
//               RS_DEPTH may be overridden at compile time: -DRS_DEPTH=4
// ============================================================

`ifndef DEFINES_VH
`define DEFINES_VH

// ---- Overridable via -D flag ----------------------------------------
`ifndef RS_DEPTH
`define RS_DEPTH 8        // Reservation station entries (4/8/16)
`endif

`ifndef ROB_DEPTH
`define ROB_DEPTH 16      // Reorder buffer entries (must be power of 2)
`endif

// ---- Fixed microarchitecture parameters ----------------------------
`define NUM_REGS    32    // Architectural register count (x0x31)
`define DATA_WIDTH  32    // Data path width in bits
`define NUM_FU      1     // Functional unit count (ALU only)
`define ALU_LATENCY 2     // Pipeline stages inside integer_alu

// Derived widths (hardcoded to avoid $clog2 in preprocessor)
`define TAG_WIDTH   4     // log2(ROB_DEPTH=16): ROB index / rename tag
`define REG_ADDR_W  5     // log2(NUM_REGS=32): architectural register index
`define SEQW        8     // Dispatch sequence counter width (age tracking)

// ---- Instruction encoding (32-bit) ---------------------------------
//   [31:27] rd   [26:22] rs1   [21:17] rs2   [16:14] opcode   [13:0] imm
`define RD_HI   31
`define RD_LO   27
`define RS1_HI  26
`define RS1_LO  22
`define RS2_HI  21
`define RS2_LO  17
`define OP_HI   16
`define OP_LO   14

// ---- ALU opcode encoding -------------------------------------------
`define OP_ADD  3'b000
`define OP_SUB  3'b001
`define OP_MUL  3'b010
`define OP_SHL  3'b011
`define OP_SHR  3'b100
`define OP_NOP  3'b111   // No-op / architectural x0 write sink

// ---- RS entry valid / invalid flag ---------------------------------
`define RS_INVALID 1'b0
`define RS_VALID   1'b1

`endif // DEFINES_VH

rtl/register_alias_table.v
// ============================================================
// Module      : register_alias_table
// Project     : Out-of-Order Issue Queue - Tesla AI Hardware Portfolio
// Author      : Mayank
// Description : Register Alias Table (RAT) / physical register file.
//               Tracks which architectural registers are in-flight and their
//               ROB tags.  Read ports include same-cycle CDB forwarding so
//               dispatch can see a result that broadcasts on the same clock.
// Parameters  : DW=32, TW=4, AW=5, NR=32
// ============================================================

`include "defines.vh"

module register_alias_table #(
    parameter DW = `DATA_WIDTH,   // Data width per register
    parameter TW = `TAG_WIDTH,    // ROB tag width
    parameter AW = `REG_ADDR_W,   // Architectural register address width
    parameter NR = `NUM_REGS      // Number of architectural registers
)(
    input  wire           clk,          // System clock
    input  wire           rst_n,        // Active-low synchronous reset
    input  wire           flush,        // Flush: clear all in-flight bits

    // Dispatch read ports (combinational, used by ooo_top at dispatch time)
    input  wire [AW-1:0]  rs1_addr,     // Source-1 architectural register index
    input  wire [AW-1:0]  rs2_addr,     // Source-2 architectural register index
    output wire           rs1_ready,    // Source-1 is ready (data valid now)
    output wire [DW-1:0]  rs1_data,     // Source-1 value (if rs1_ready)
    output wire [TW-1:0]  rs1_tag,      // Source-1 in-flight ROB tag (if !rs1_ready)
    output wire           rs2_ready,    // Source-2 is ready (data valid now)
    output wire [DW-1:0]  rs2_data,     // Source-2 value (if rs2_ready)
    output wire [TW-1:0]  rs2_tag,      // Source-2 in-flight ROB tag (if !rs2_ready)

    // Rename write port (from ooo_top at dispatch, clocked)
    input  wire           rename_valid, // Dispatch is occurring this cycle
    input  wire [AW-1:0]  rename_rd,    // Architectural destination register
    input  wire [TW-1:0]  rename_tag,   // ROB slot assigned to this instruction

    // Commit port (from ROB head, clocked)
    input  wire           commit_valid, // ROB is committing head entry this cycle
    input  wire [AW-1:0]  commit_rd,    // Architectural register being written
    input  wire [DW-1:0]  commit_data,  // Committed value
    input  wire [TW-1:0]  commit_tag,   // ROB tag of committing instruction (WAW guard)

    // CDB snoop (combinational, used for read-port forwarding AND clocked capture)
    input  wire           cdb_valid,    // Result available on CDB this cycle
    input  wire [TW-1:0]  cdb_tag,      // Tag of result on CDB
    input  wire [DW-1:0]  cdb_data      // Data of result on CDB
);

// ---- Register state arrays -----------------------------------------
reg [DW-1:0] reg_data      [0:NR-1];   // Committed / forwarded register values
reg [TW-1:0] reg_tag       [0:NR-1];   // Current rename tag (valid when in_flight)
reg          reg_in_flight [0:NR-1];   // 1 = a pending instruction will write this reg

// ---- Combinational read with same-cycle CDB forwarding -------------
// If a register is in-flight and its tag is being broadcast on the CDB
// right now, the dispatching instruction can capture it immediately.
wire rs1_cdb_hit = reg_in_flight[rs1_addr] && cdb_valid && (reg_tag[rs1_addr] == cdb_tag);
wire rs2_cdb_hit = reg_in_flight[rs2_addr] && cdb_valid && (reg_tag[rs2_addr] == cdb_tag);

assign rs1_ready = !reg_in_flight[rs1_addr] || rs1_cdb_hit;
assign rs1_data  = rs1_cdb_hit ? cdb_data : reg_data[rs1_addr];
assign rs1_tag   = reg_tag[rs1_addr];

assign rs2_ready = !reg_in_flight[rs2_addr] || rs2_cdb_hit;
assign rs2_data  = rs2_cdb_hit ? cdb_data : reg_data[rs2_addr];
assign rs2_tag   = reg_tag[rs2_addr];

// ---- Sequential: rename, commit, CDB data capture -----------------
integer r;
always @(posedge clk) begin
    if (!rst_n) begin
        for (r = 0; r < NR; r = r + 1) begin
            reg_data[r]      <= {DW{1'b0}};
            reg_tag[r]       <= {TW{1'b0}};
            reg_in_flight[r] <= 1'b0;
        end
    end else if (flush) begin
        // Flush: retire all in-flight state; data already written by CDB is kept
        for (r = 0; r < NR; r = r + 1)
            reg_in_flight[r] <= 1'b0;
    end else begin
        // CDB capture: forward result into architectural register data array
        if (cdb_valid) begin
            for (r = 0; r < NR; r = r + 1) begin
                if (reg_in_flight[r] && (reg_tag[r] == cdb_tag))
                    reg_data[r] <= cdb_data;
            end
        end

        // Commit: ROB head retires - clear in_flight only if tags still match
        // (WAW guard: a newer rename may have already overwritten reg_tag)
        if (commit_valid && (commit_rd != {AW{1'b0}})) begin
            reg_data[commit_rd] <= commit_data;
            if (reg_tag[commit_rd] == commit_tag)
                reg_in_flight[commit_rd] <= 1'b0;
        end

        // Rename: new dispatch creates a new mapping for rd
        // Processed AFTER commit so a commit+rename of the same rd in the
        // same cycle leaves the register marked in-flight (the rename wins).
        if (rename_valid && (rename_rd != {AW{1'b0}})) begin
            reg_tag[rename_rd]       <= rename_tag;
            reg_in_flight[rename_rd] <= 1'b1;
        end
    end
end

endmodule

tb/tb_rat.v
`timescale 1ns/1ps
`include "rtl/defines.vh"

// ============================================================
// Testbench : tb_rat
// Tests     : 1) Fresh register returns ready  2) Rename marks in-flight
//             3) WAW guard at commit  4) CDB same-cycle forwarding
//             5) Flush clears in-flight bits
// ============================================================

module tb_rat;

localparam DW  = 32;
localparam TW  = 4;
localparam AW  = 5;
localparam NR  = 32;
localparam CLK = 10;

reg        clk, rst_n, flush;
reg [AW-1:0] rs1_addr, rs2_addr;
wire         rs1_ready, rs2_ready;
wire [DW-1:0] rs1_data, rs2_data;
wire [TW-1:0] rs1_tag, rs2_tag;
reg          rename_valid;
reg [AW-1:0] rename_rd;
reg [TW-1:0] rename_tag;
reg          commit_valid;
reg [AW-1:0] commit_rd;
reg [DW-1:0] commit_data;
reg [TW-1:0] commit_tag;
reg          cdb_valid;
reg [TW-1:0] cdb_tag;
reg [DW-1:0] cdb_data;

integer errors;

register_alias_table #(.DW(DW),.TW(TW),.AW(AW),.NR(NR)) dut (
    .clk(clk), .rst_n(rst_n), .flush(flush),
    .rs1_addr(rs1_addr), .rs2_addr(rs2_addr),
    .rs1_ready(rs1_ready), .rs1_data(rs1_data), .rs1_tag(rs1_tag),
    .rs2_ready(rs2_ready), .rs2_data(rs2_data), .rs2_tag(rs2_tag),
    .rename_valid(rename_valid), .rename_rd(rename_rd), .rename_tag(rename_tag),
    .commit_valid(commit_valid), .commit_rd(commit_rd),
    .commit_data(commit_data), .commit_tag(commit_tag),
    .cdb_valid(cdb_valid), .cdb_tag(cdb_tag), .cdb_data(cdb_data)
);

initial clk = 0;
always #(CLK/2) clk = ~clk;

initial begin
    $dumpfile("sim/waves/rat_tb.vcd");
    $dumpvars(0, tb_rat);
    errors = 0;

    rst_n = 0; flush = 0;
    rs1_addr = 0; rs2_addr = 0;
    rename_valid = 0; rename_rd = 0; rename_tag = 0;
    commit_valid = 0; commit_rd = 0; commit_data = 0; commit_tag = 0;
    cdb_valid = 0; cdb_tag = 0; cdb_data = 0;
    repeat(4) @(posedge clk);
    rst_n = 1; #1;

    // TEST 1: Fresh register is ready (no in-flight bit)
    $display("TEST 1: Fresh register returns ready");
    rs1_addr = 5'd5;
    #1;
    if (!rs1_ready) begin
        $display("  FAIL: x5 should be ready after reset");
        errors = errors + 1;
    end else
        $display("  PASS: x5 is ready");

    // TEST 2: Rename marks register in-flight
    $display("TEST 2: Rename marks register in-flight");
    rename_valid = 1; rename_rd = 5'd5; rename_tag = 4'd3;
    @(posedge clk); #1;
    rename_valid = 0;
    rs1_addr = 5'd5;
    #1;
    if (rs1_ready) begin
        $display("  FAIL: x5 should be in-flight after rename");
        errors = errors + 1;
    end else if (rs1_tag !== 4'd3) begin
        $display("  FAIL: rs1_tag=%0d expected 3", rs1_tag);
        errors = errors + 1;
    end else
        $display("  PASS: x5 in-flight with tag=%0d", rs1_tag);

    // TEST 3: WAW guard - rename twice, old commit doesn't clear in-flight
    $display("TEST 3: WAW guard at commit");
    // First rename: x5  tag 3 (already done)
    // Second rename: x5  tag 7 (newer instruction)
    rename_valid = 1; rename_rd = 5'd5; rename_tag = 4'd7;
    @(posedge clk); #1;
    rename_valid = 0;
    // Commit tag 3 (the older one) - should NOT clear in-flight (tag 7 is current)
    commit_valid = 1; commit_rd = 5'd5; commit_data = 32'hAAAA; commit_tag = 4'd3;
    @(posedge clk); #1;
    commit_valid = 0; #1;
    rs1_addr = 5'd5;
    #1;
    if (rs1_ready) begin
        $display("  FAIL: WAW guard failed - in_flight wrongly cleared by old commit");
        errors = errors + 1;
    end else
        $display("  PASS: WAW guard correct, x5 still in-flight (tag 7 current)");
    // Now commit the newer tag 7 - should clear
    commit_valid = 1; commit_rd = 5'd5; commit_data = 32'hBBBB; commit_tag = 4'd7;
    @(posedge clk); #1;
    commit_valid = 0; #1;
    rs1_addr = 5'd5;
    #1;
    if (!rs1_ready) begin
        $display("  FAIL: x5 should be ready after tag-7 commit");
        errors = errors + 1;
    end else
        $display("  PASS: x5 ready after tag-7 commit, data=%h", rs1_data);

    // TEST 4: CDB same-cycle forwarding
    $display("TEST 4: CDB same-cycle forwarding at dispatch");
    rename_valid = 1; rename_rd = 5'd10; rename_tag = 4'd5;
    @(posedge clk); #1;
    rename_valid = 0;
    // Now x10 is in-flight on tag 5
    // Drive CDB with tag 5 simultaneously with reading rs1
    cdb_valid = 1; cdb_tag = 4'd5; cdb_data = 32'hC0FFEE;
    rs1_addr = 5'd10;
    #1;
    // RAT should forward: rs1_ready=1, rs1_data=cdb_data
    if (!rs1_ready) begin
        $display("  FAIL: CDB forwarding not working - rs1_ready=0");
        errors = errors + 1;
    end else if (rs1_data !== 32'hC0FFEE) begin
        $display("  FAIL: CDB forward wrong data: got %h expected C0FFEE", rs1_data);
        errors = errors + 1;
    end else
        $display("  PASS: CDB forwarded data=%h to dispatch read", rs1_data);
    cdb_valid = 0;
    @(posedge clk); #1;

    // TEST 5: Flush clears all in-flight bits
    $display("TEST 5: Flush clears in-flight");
    rename_valid = 1; rename_rd = 5'd15; rename_tag = 4'd9;
    @(posedge clk); #1; rename_valid = 0;
    flush = 1; @(posedge clk); #1; flush = 0; #1;
    rs1_addr = 5'd15;
    #1;
    if (!rs1_ready) begin
        $display("  FAIL: x15 still in-flight after flush");
        errors = errors + 1;
    end else
        $display("  PASS: x15 ready after flush");

    $display("--------------------------------------------");
    if (errors == 0)
        $display("register_alias_table TB: RESULT: PASS");
    else
        $display("register_alias_table TB: %0d errors, RESULT: FAIL", errors);
    $display("--------------------------------------------");
    $finish;
end

initial begin
    #100000; $display("TIMEOUT"); $finish;
end

endmodule

sim/waves/rat_tb.vcd
$date
	Sat Jun 13 20:48:52 2026
$end
$version
	Icarus Verilog
$end
$timescale
	1ps
$end
$scope module tb_rat $end
$var wire 4 ! rs2_tag [3:0] $end
$var wire 1 " rs2_ready $end
$var wire 32 # rs2_data [31:0] $end
$var wire 4 $ rs1_tag [3:0] $end
$var wire 1 % rs1_ready $end
$var wire 32 & rs1_data [31:0] $end
$var reg 32 ' cdb_data [31:0] $end
$var reg 4 ( cdb_tag [3:0] $end
$var reg 1 ) cdb_valid $end
$var reg 1 * clk $end
$var reg 32 + commit_data [31:0] $end
$var reg 5 , commit_rd [4:0] $end
$var reg 4 - commit_tag [3:0] $end
$var reg 1 . commit_valid $end
$var reg 1 / flush $end
$var reg 5 0 rename_rd [4:0] $end
$var reg 4 1 rename_tag [3:0] $end
$var reg 1 2 rename_valid $end
$var reg 5 3 rs1_addr [4:0] $end
$var reg 5 4 rs2_addr [4:0] $end
$var reg 1 5 rst_n $end
$var integer 32 6 errors [31:0] $end
$scope module dut $end
$var wire 32 7 cdb_data [31:0] $end
$var wire 4 8 cdb_tag [3:0] $end
$var wire 1 ) cdb_valid $end
$var wire 1 * clk $end
$var wire 32 9 commit_data [31:0] $end
$var wire 5 : commit_rd [4:0] $end
$var wire 4 ; commit_tag [3:0] $end
$var wire 1 . commit_valid $end
$var wire 1 / flush $end
$var wire 5 < rename_rd [4:0] $end
$var wire 4 = rename_tag [3:0] $end
$var wire 1 2 rename_valid $end
$var wire 5 > rs1_addr [4:0] $end
$var wire 1 ? rs1_cdb_hit $end
$var wire 1 % rs1_ready $end
$var wire 4 @ rs1_tag [3:0] $end
$var wire 5 A rs2_addr [4:0] $end
$var wire 1 B rs2_cdb_hit $end
$var wire 1 " rs2_ready $end
$var wire 4 C rs2_tag [3:0] $end
$var wire 1 5 rst_n $end
$var wire 32 D rs2_data [31:0] $end
$var wire 32 E rs1_data [31:0] $end
$var integer 32 F r [31:0] $end
$upscope $end
$upscope $end
$enddefinitions $end
#0
$dumpvars
bx F
bx E
bx D
bx C
0B
b0 A
bx @
0?
b0 >
b0 =
b0 <
b0 ;
b0 :
b0 9
b0 8
b0 7
b0 6
05
b0 4
b0 3
02
b0 1
b0 0
0/
0.
b0 -
b0 ,
b0 +
0*
0)
b0 (
b0 '
bx &
x%
bx $
bx #
x"
bx !
$end
#5000
1%
1"
b0 &
b0 E
b0 #
b0 D
b0 $
b0 @
b0 !
b0 C
b100000 F
1*
#10000
0*
#15000
b100000 F
1*
#20000
0*
#25000
b100000 F
1*
#30000
0*
#35000
15
b100000 F
1*
#36000
b101 3
b101 >
#37000
b11 1
b11 =
b101 0
b101 <
12
#40000
0*
#45000
0%
b11 $
b11 @
1*
#46000
02
#47000
b111 1
b111 =
12
#50000
0*
#55000
b111 $
b111 @
1*
#56000
b11 -
b11 ;
b1010101010101010 +
b1010101010101010 9
b101 ,
b101 :
1.
02
#60000
0*
#65000
b1010101010101010 &
b1010101010101010 E
1*
#66000
0.
#68000
b111 -
b111 ;
b1011101110111011 +
b1011101110111011 9
1.
#70000
0*
#75000
1%
b1011101110111011 &
b1011101110111011 E
1*
#76000
0.
#78000
b101 1
b101 =
b1010 0
b1010 <
12
#80000
0*
#85000
1*
#86000
1?
1%
b110000001111111111101110 &
b110000001111111111101110 E
b101 $
b101 @
b1010 3
b1010 >
b110000001111111111101110 '
b110000001111111111101110 7
b101 (
b101 8
1)
02
#87000
0%
b0 &
b0 E
0?
0)
#90000
0*
#95000
1*
#96000
b1001 1
b1001 =
b1111 0
b1111 <
12
#100000
0*
#105000
1*
#106000
1/
02
#110000
0*
#115000
1%
b100000 F
1*
#116000
0/
#117000
b1001 $
b1001 @
b1111 3
b1111 >
