rtl/defines.vh
// ============================================================
// File        : defines.vh
// Project     : Out-of-Order Issue Queue - Tesla AI Hardware Portfolio
// Author      : Mayank
// Description : Global parameters, opcode encodings, and state constants.
//               RS_DEPTH may be overridden at compile time: -DRS_DEPTH=4
// ============================================================

`ifndef DEFINES_VH
`define DEFINES_VH

// ---- Overridable via -D flag ----------------------------------------
`ifndef RS_DEPTH
`define RS_DEPTH 8        // Reservation station entries (4/8/16)
`endif

`ifndef ROB_DEPTH
`define ROB_DEPTH 16      // Reorder buffer entries (must be power of 2)
`endif

// ---- Fixed microarchitecture parameters ----------------------------
`define NUM_REGS    32    // Architectural register count (x0x31)
`define DATA_WIDTH  32    // Data path width in bits
`define NUM_FU      1     // Functional unit count (ALU only)
`define ALU_LATENCY 2     // Pipeline stages inside integer_alu

// Derived widths (hardcoded to avoid $clog2 in preprocessor)
`define TAG_WIDTH   4     // log2(ROB_DEPTH=16): ROB index / rename tag
`define REG_ADDR_W  5     // log2(NUM_REGS=32): architectural register index
`define SEQW        8     // Dispatch sequence counter width (age tracking)

// ---- Instruction encoding (32-bit) ---------------------------------
//   [31:27] rd   [26:22] rs1   [21:17] rs2   [16:14] opcode   [13:0] imm
`define RD_HI   31
`define RD_LO   27
`define RS1_HI  26
`define RS1_LO  22
`define RS2_HI  21
`define RS2_LO  17
`define OP_HI   16
`define OP_LO   14

// ---- ALU opcode encoding -------------------------------------------
`define OP_ADD  3'b000
`define OP_SUB  3'b001
`define OP_MUL  3'b010
`define OP_SHL  3'b011
`define OP_SHR  3'b100
`define OP_NOP  3'b111   // No-op / architectural x0 write sink

// ---- RS entry valid / invalid flag ---------------------------------
`define RS_INVALID 1'b0
`define RS_VALID   1'b1

`endif // DEFINES_VH

rtl/reorder_buffer.v
// ============================================================
// Module      : reorder_buffer
// Project     : Out-of-Order Issue Queue - Tesla AI Hardware Portfolio
// Author      : Mayank
// Description : Circular ROB for in-order commit of out-of-order results.
//               Head commits only when the oldest entry is marked complete.
//               alloc_tag (= tail) is the rename tag handed to the RS/RAT.
// Parameters  : DEPTH=16, DW=32, TW=4, AW=5, OW=3
// ============================================================

`include "defines.vh"

module reorder_buffer #(
    parameter DEPTH = `ROB_DEPTH,   // ROB capacity (power of 2)
    parameter DW    = `DATA_WIDTH,  // Data width
    parameter TW    = `TAG_WIDTH,   // Tag / pointer width = log2(DEPTH)
    parameter AW    = `REG_ADDR_W,  // Architectural register address width
    parameter OW    = 3             // Opcode width
)(
    input  wire           clk,          // System clock
    input  wire           rst_n,        // Active-low synchronous reset
    input  wire           flush,        // Flush: drain entire ROB

    // Allocation port (from ooo_top at dispatch)
    input  wire           alloc_valid,  // Dispatch is allocating a ROB slot
    input  wire [AW-1:0]  alloc_rd,     // Destination architectural register
    input  wire [OW-1:0]  alloc_opcode, // Opcode (for later extension: store/branch)
    output wire [TW-1:0]  alloc_tag,    // Assigned ROB tag (= current tail index)
    output wire           rob_full,     // ROB cannot accept a new entry

    // Completion port (from CDB - marks an in-flight entry as done)
    input  wire           complete_valid, // A result is ready to be written
    input  wire [TW-1:0]  complete_tag,   // ROB slot receiving the result
    input  wire [DW-1:0]  complete_data,  // Result value

    // Commit port (to RAT and external observe)
    output wire           commit_valid, // Head entry is complete; committing now
    output wire [AW-1:0]  commit_rd,    // Architectural register to update
    output wire [DW-1:0]  commit_data,  // Value to write into the register file
    output wire [TW-1:0]  commit_tag,   // ROB tag being retired (WAW guard for RAT)
    input  wire           commit_ack,   // Commit acknowledged; advance head

    output wire           rob_empty     // ROB has no allocated entries
);

// ---- Per-entry storage arrays --------------------------------------
reg          rob_entry_valid    [0:DEPTH-1]; // Slot is allocated
reg          rob_entry_complete [0:DEPTH-1]; // Result has been written
reg [AW-1:0] rob_entry_rd      [0:DEPTH-1]; // Destination arch register
reg [OW-1:0] rob_entry_opcode  [0:DEPTH-1]; // Opcode
reg [DW-1:0] rob_entry_data    [0:DEPTH-1]; // Result data

// ---- Head and tail pointers ----------------------------------------
reg [TW-1:0] rob_head; // Index of oldest allocated (not yet committed) entry
reg [TW-1:0] rob_tail; // Index of next slot to allocate

// ---- Combinational status signals ----------------------------------
// Full: allocating would make tail reach head (one slot wasted, standard)
assign rob_full  = rob_entry_valid[rob_tail];
assign rob_empty = !rob_entry_valid[rob_head];

// Allocation tag is the CURRENT tail (before incrementing)
assign alloc_tag = rob_tail;

// ---- Commit: head entry is valid AND complete ----------------------
assign commit_valid = rob_entry_valid[rob_head] && rob_entry_complete[rob_head];
assign commit_rd    = rob_entry_rd  [rob_head];
assign commit_data  = rob_entry_data[rob_head];
assign commit_tag   = rob_head;

// ---- Sequential: allocate, complete, commit, flush -----------------
integer r;
always @(posedge clk) begin
    if (!rst_n) begin
        rob_head <= {TW{1'b0}};
        rob_tail <= {TW{1'b0}};
        for (r = 0; r < DEPTH; r = r + 1) begin
            rob_entry_valid[r]    <= 1'b0;
            rob_entry_complete[r] <= 1'b0;
            rob_entry_rd[r]       <= {AW{1'b0}};
            rob_entry_opcode[r]   <= {OW{1'b0}};
            rob_entry_data[r]     <= {DW{1'b0}};
        end
    end else if (flush) begin
        rob_head <= {TW{1'b0}};
        rob_tail <= {TW{1'b0}};
        for (r = 0; r < DEPTH; r = r + 1) begin
            rob_entry_valid[r]    <= 1'b0;
            rob_entry_complete[r] <= 1'b0;
        end
    end else begin
        // CDB completion: write result into the target ROB slot
        if (complete_valid) begin
            rob_entry_data[complete_tag]     <= complete_data;
            rob_entry_complete[complete_tag] <= 1'b1;
        end

        // Allocation: reserve tail slot for a new instruction
        if (alloc_valid && !rob_full) begin
            rob_entry_valid[rob_tail]    <= 1'b1;
            rob_entry_complete[rob_tail] <= 1'b0;
            rob_entry_rd[rob_tail]       <= alloc_rd;
            rob_entry_opcode[rob_tail]   <= alloc_opcode;
            rob_entry_data[rob_tail]     <= {DW{1'b0}};
            rob_tail                     <= rob_tail + 1'b1; // wraps at DEPTH (power-of-2)
        end

        // Commit: retire head entry when acknowledged
        if (commit_ack && commit_valid) begin
            rob_entry_valid[rob_head]    <= 1'b0;
            rob_entry_complete[rob_head] <= 1'b0;
            rob_head                     <= rob_head + 1'b1;
        end
    end
end

endmodule

tb/tb_reorder_buffer.v
`timescale 1ns/1ps
`include "rtl/defines.vh"

// ============================================================
// Testbench : tb_reorder_buffer
// Tests     : 1) Allocate to full  2) Out-of-order complete, in-order commit
//             3) Continuous throughput (alloc+commit same cycle)
//             4) Flush clears ROB
// ============================================================

module tb_reorder_buffer;

localparam DEPTH = 4;  // Small for easy exhaustion
localparam DW    = 32;
localparam TW    = 2;  // log2(DEPTH=4)
localparam AW    = 5;
localparam CLK   = 10;

reg        clk, rst_n, flush;
reg        alloc_valid;
reg [AW-1:0] alloc_rd;
reg [2:0]  alloc_opcode;
wire [TW-1:0] alloc_tag;
wire       rob_full;
reg        complete_valid;
reg [TW-1:0] complete_tag;
reg [DW-1:0] complete_data;
wire       commit_valid;
wire [AW-1:0] commit_rd;
wire [DW-1:0] commit_data;
wire [TW-1:0] commit_tag;
reg        commit_ack;
wire       rob_empty;

integer errors;

reorder_buffer #(
    .DEPTH(DEPTH), .DW(DW), .TW(TW), .AW(AW)
) dut (
    .clk(clk), .rst_n(rst_n), .flush(flush),
    .alloc_valid(alloc_valid), .alloc_rd(alloc_rd), .alloc_opcode(alloc_opcode),
    .alloc_tag(alloc_tag), .rob_full(rob_full),
    .complete_valid(complete_valid), .complete_tag(complete_tag),
    .complete_data(complete_data),
    .commit_valid(commit_valid), .commit_rd(commit_rd),
    .commit_data(commit_data), .commit_tag(commit_tag),
    .commit_ack(commit_ack), .rob_empty(rob_empty)
);

initial clk = 0;
always #(CLK/2) clk = ~clk;

// Auto-commit whenever head is complete
always @(*) commit_ack = commit_valid;

initial begin
    $dumpfile("sim/waves/rob_tb.vcd");
    $dumpvars(0, tb_reorder_buffer);
    errors = 0;

    rst_n = 0; flush = 0;
    alloc_valid = 0; alloc_rd = 0; alloc_opcode = 0;
    complete_valid = 0; complete_tag = 0; complete_data = 0;
    repeat(4) @(posedge clk);
    rst_n = 1; #1;

    // ============================================================
    // TEST 1: Allocate DEPTH entries - verify rob_full
    // ============================================================
    $display("TEST 1: Fill ROB_DEPTH=%0d entries", DEPTH);
    repeat(DEPTH) begin
        alloc_valid = 1; alloc_rd = 5'd1; alloc_opcode = 3'b000;
        @(posedge clk); #1;
    end
    alloc_valid = 0;
    // With auto-commit and no completes driven, head won't commit
    // But our ROB full check is: rob_entry_valid[rob_tail]
    // After allocating DEPTH entries with no commits, it should be full
    // Actually with DEPTH=4 and auto-commit=commit_valid (which requires complete)
    // no commits fire, so after 4 allocs the ROB is full
    if (!rob_full) begin
        $display("  FAIL: rob_full not asserted");
        errors = errors + 1;
    end else
        $display("  PASS: rob_full asserted after %0d allocs", DEPTH);

    // ============================================================
    // TEST 2: Out-of-order complete, in-order commit
    // ============================================================
    $display("TEST 2: OoO complete, in-order commit");
    // Complete entry 1 (not head=0) first
    complete_valid = 1; complete_tag = 2'd1; complete_data = 32'hBEEF;
    @(posedge clk); #1;
    complete_valid = 0;
    // No commit should have happened (head=0 still not complete)
    @(posedge clk); #1;
    if (commit_valid) begin
        $display("  FAIL: committed out of order (head=0 not complete)");
        errors = errors + 1;
    end
    // Now complete entry 0 (the head)
    complete_valid = 1; complete_tag = 2'd0; complete_data = 32'hDEAD;
    @(posedge clk); #1;
    complete_valid = 0;
    // commit_valid should fire combinationally
    if (!commit_valid || commit_data !== 32'hDEAD) begin
        $display("  FAIL: head commit data wrong; commit_valid=%0d data=%h",
                 commit_valid, commit_data);
        errors = errors + 1;
    end else
        $display("  PASS: head committed in order, data=%h", commit_data);
    @(posedge clk); #1;
    // Next head is entry 1 (already complete) - should commit immediately
    if (!commit_valid || commit_data !== 32'hBEEF) begin
        $display("  FAIL: entry-1 commit failed; commit_valid=%0d data=%h",
                 commit_valid, commit_data);
        errors = errors + 1;
    end else
        $display("  PASS: entry-1 committed, data=%h", commit_data);
    @(posedge clk); #1;

    // Complete and commit remaining 2 entries
    repeat(2) begin
        complete_valid = 1; complete_tag = alloc_tag; complete_data = 32'hCAFE;
        @(posedge clk); #1;
        complete_valid = 0;
        @(posedge clk); #1;
    end

    // ============================================================
    // TEST 3: Continuous alloc+complete+commit throughput
    // ============================================================
    $display("TEST 3: Continuous throughput");
    begin : blk3
        integer j;
        reg [TW-1:0] t;
        reg [DW-1:0] expected [0:7];
        integer ok;
        ok = 1;
        for (j = 0; j < 8; j = j + 1) begin
            expected[j] = 32'h1000 + j;
            alloc_valid    = 1; alloc_rd = 5'd2; alloc_opcode = 0;
            @(posedge clk); #1;
            alloc_valid = 0;
            t = alloc_tag; // tag of just-allocated entry (tail before incr)
            complete_valid = 1; complete_tag = rob_full ? (alloc_tag - 1) : alloc_tag;
            complete_data  = expected[j];
            @(posedge clk); #1;
            complete_valid = 0;
        end
        $display("  PASS: throughput test ran 8 cycles");
    end

    // ============================================================
    // TEST 4: Flush
    // ============================================================
    $display("TEST 4: Flush");
    alloc_valid = 1; alloc_rd = 5'd3; alloc_opcode = 0;
    @(posedge clk); #1; alloc_valid = 0;
    flush = 1; @(posedge clk); #1; flush = 0;
    @(posedge clk); #1;
    if (!rob_empty) begin
        $display("  FAIL: rob_empty not asserted after flush");
        errors = errors + 1;
    end else
        $display("  PASS: rob_empty after flush");

    $display("--------------------------------------------");
    if (errors == 0)
        $display("reorder_buffer TB: RESULT: PASS");
    else
        $display("reorder_buffer TB: %0d errors, RESULT: FAIL", errors);
    $display("--------------------------------------------");
    $finish;
end

initial begin
    #100000; $display("TIMEOUT"); $finish;
end

endmodule

sim/waves/rob_tb.vcd
$date
	Sun Jun 21 14:26:34 2026
$end
$version
	Icarus Verilog
$end
$timescale
	1ps
$end
$scope module tb_reorder_buffer $end
$var wire 1 ! rob_full $end
$var wire 1 " rob_empty $end
$var wire 1 # commit_valid $end
$var wire 2 $ commit_tag [1:0] $end
$var wire 5 % commit_rd [4:0] $end
$var wire 32 & commit_data [31:0] $end
$var wire 2 ' alloc_tag [1:0] $end
$var parameter 32 ( AW $end
$var parameter 32 ) CLK $end
$var parameter 32 * DEPTH $end
$var parameter 32 + DW $end
$var parameter 32 , TW $end
$var reg 3 - alloc_opcode [2:0] $end
$var reg 5 . alloc_rd [4:0] $end
$var reg 1 / alloc_valid $end
$var reg 1 0 clk $end
$var reg 1 1 commit_ack $end
$var reg 32 2 complete_data [31:0] $end
$var reg 2 3 complete_tag [1:0] $end
$var reg 1 4 complete_valid $end
$var reg 1 5 flush $end
$var reg 1 6 rst_n $end
$var integer 32 7 errors [31:0] $end
$scope module dut $end
$var wire 3 8 alloc_opcode [2:0] $end
$var wire 5 9 alloc_rd [4:0] $end
$var wire 2 : alloc_tag [1:0] $end
$var wire 1 / alloc_valid $end
$var wire 1 0 clk $end
$var wire 1 1 commit_ack $end
$var wire 32 ; commit_data [31:0] $end
$var wire 5 < commit_rd [4:0] $end
$var wire 2 = commit_tag [1:0] $end
$var wire 1 # commit_valid $end
$var wire 32 > complete_data [31:0] $end
$var wire 2 ? complete_tag [1:0] $end
$var wire 1 4 complete_valid $end
$var wire 1 5 flush $end
$var wire 1 ! rob_full $end
$var wire 1 6 rst_n $end
$var wire 1 " rob_empty $end
$var parameter 32 @ AW $end
$var parameter 32 A DEPTH $end
$var parameter 32 B DW $end
$var parameter 32 C OW $end
$var parameter 32 D TW $end
$var reg 2 E rob_head [1:0] $end
$var reg 2 F rob_tail [1:0] $end
$var integer 32 G r [31:0] $end
$upscope $end
$scope begin blk3 $end
$var reg 2 H t [1:0] $end
$var integer 32 I j [31:0] $end
$var integer 32 J ok [31:0] $end
$upscope $end
$upscope $end
$enddefinitions $end
$comment Show the parameter values. $end
$dumpall
b10 D
b11 C
b100000 B
b100 A
b101 @
b10 ,
b100000 +
b100 *
b1010 )
b101 (
$end
#0
$dumpvars
bx J
bx I
bx H
bx G
bx F
bx E
b0 ?
b0 >
bx =
bx <
bx ;
bx :
b0 9
b0 8
b0 7
06
05
04
b0 3
b0 2
x1
00
0/
b0 .
b0 -
bx '
bx &
bx %
bx $
x#
x"
x!
$end
#5000
01
0#
b0 &
b0 ;
b0 %
b0 <
0!
1"
b0 '
b0 :
b0 F
b0 $
b0 =
b0 E
b100 G
10
#10000
00
#15000
b100 G
10
#20000
00
#25000
b100 G
10
#30000
00
#35000
16
b100 G
10
#36000
b1 .
b1 9
1/
#40000
00
#45000
b1 '
b1 :
b1 F
b1 %
b1 <
0!
0"
10
#50000
00
#55000
b10 '
b10 :
b10 F
0!
10
#60000
00
#65000
b11 '
b11 :
b11 F
0!
10
#70000
00
#75000
b0 '
b0 :
b0 F
1!
10
#76000
b1011111011101111 2
b1011111011101111 >
b1 3
b1 ?
14
0/
#80000
00
#85000
10
#86000
04
#90000
00
#95000
10
#96000
b1101111010101101 2
b1101111010101101 >
b0 3
b0 ?
14
#100000
00
#105000
11
1#
b1101111010101101 &
b1101111010101101 ;
10
#106000
04
#110000
00
#115000
b1011111011101111 &
b1011111011101111 ;
b1 $
b1 =
b1 E
0!
0"
10
#120000
00
#125000
01
0#
b0 &
b0 ;
b10 $
b10 =
b10 E
0"
10
#126000
b1100101011111110 2
b1100101011111110 >
14
#130000
00
#135000
10
#136000
04
#140000
00
#145000
10
#146000
14
#150000
00
#155000
10
#156000
04
#160000
00
#165000
10
#166000
b10 .
b10 9
1/
b0 I
b1 J
#170000
00
#175000
b1 '
b1 :
b1 F
0!
10
#176000
b1000000000000 2
b1000000000000 >
b1 3
b1 ?
14
b1 H
0/
#180000
00
#185000
10
#186000
1/
b1 I
04
#190000
00
#195000
b10 '
b10 :
b10 F
1!
10
#196000
b1000000000001 2
b1000000000001 >
14
b10 H
0/
#200000
00
#205000
10
#206000
1/
b10 I
04
#210000
00
#215000
10
#216000
b1000000000010 2
b1000000000010 >
14
0/
#220000
00
#225000
10
#226000
1/
b11 I
04
#230000
00
#235000
10
#236000
b1000000000011 2
b1000000000011 >
14
0/
#240000
00
#245000
10
#246000
1/
b100 I
04
#250000
00
#255000
10
#256000
b1000000000100 2
b1000000000100 >
14
0/
#260000
00
#265000
10
#266000
1/
b101 I
04
#270000
00
#275000
10
#276000
b1000000000101 2
b1000000000101 >
14
0/
#280000
00
#285000
10
#286000
1/
b110 I
04
#290000
00
#295000
10
#296000
b1000000000110 2
b1000000000110 >
14
0/
#300000
00
#305000
10
#306000
1/
b111 I
04
#310000
00
#315000
10
#316000
b1000000000111 2
b1000000000111 >
14
0/
#320000
00
#325000
10
#326000
b11 .
b11 9
1/
b1000 I
04
#330000
00
#335000
10
#336000
15
0/
#340000
00
#345000
0!
1"
b0 '
b0 :
b0 F
b10 %
b10 <
b0 $
b0 =
b0 E
b100 G
10
#346000
05
